[
  {
    "inputs": [
      {
        "internalType": "uint256",
        "name": "",
        "type": "uint256"
      },
      {
        "internalType": "uint40",
        "name": "",
        "type": "uint40"
      },
      {
        "internalType": "uint40",
        "name": "",
        "type": "uint40"
      },
      {
        "internalType": "uint96",
        "name": "",
        "type": "uint96"
      }
    ],
    "name": "addTokensToEpochRange",
    "outputs": [],
    "stateMutability": "nonpayable",
    "type": "function"
  }
]
